binsize/.gitignore
binsize/__init__.py
binsize/cli/__init__.py
binsize/cli/binsize.py
binsize/cli/build.py
binsize/cli/commit.py
binsize/cli/compare.py
binsize/cli/get.py
binsize/cli/history.py
binsize/cli/tree.py
binsize/lib/__init__.py
binsize/lib/api.py
binsize/lib/binary_size.py
binsize/lib/build_definition_loader.py
binsize/lib/common.py
binsize/lib/data_handler.py
binsize/lib/data_loader.py
binsize/lib/map_file_analyzer.py
binsize/lib/map_file_includer.py
binsize/lib/row_handler_c.py
binsize/lib/row_handler_common.py
binsize/lib/row_handler_mpy.py
binsize/lib/row_handler_rust.py
binsize/lib/source_definition_cache.py
binsize/plugins/__init__.py
binsize/plugins/size_tree.py
binsize/plugins/statistics.py
binsize/settings.py
binsize/settings_template.json
binsize/user_data.py
binsize/utils.py
binsize-0.1.4.dist-info/LICENSE
binsize-0.1.4.dist-info/METADATA
binsize-0.1.4.dist-info/WHEEL
binsize-0.1.4.dist-info/entry_points.txt
binsize-0.1.4.dist-info/RECORD
