Metadata-Version: 2.3
Name: binsize
Version: 0.1.4
Summary: Tool to analyze the size of a binary from .elf file
License: MIT
Keywords: binary size,code size,.elf file
Author: SatoshiLabs
Author-email: info@satoshilabs.com
Requires-Python: >=3.7,<4.0
Classifier: License :: OSI Approved :: MIT License
Classifier: Programming Language :: Python :: 3
Classifier: Programming Language :: Python :: 3.7
Classifier: Programming Language :: Python :: 3.8
Classifier: Programming Language :: Python :: 3.9
Classifier: Programming Language :: Python :: 3.10
Classifier: Programming Language :: Python :: 3.11
Classifier: Programming Language :: Python :: 3.12
Classifier: Programming Language :: Python :: 3.13
Requires-Dist: click (>=8.1.3,<9.0.0)
Requires-Dist: platformdirs (>=2.5)
Requires-Dist: termcolor (>=2)
Requires-Dist: typing-extensions
Project-URL: Repository, https://github.com/grdddj/binsize
